dagster_obstore/__init__.py
dagster_obstore/py.typed
dagster_obstore/_base/__init__.py
dagster_obstore/_base/log_manager.py
dagster_obstore/azure/__init__.py
dagster_obstore/azure/compute_log_manager.py
dagster_obstore/azure/resource.py
dagster_obstore/gcs/__init__.py
dagster_obstore/gcs/compute_log_manager.py
dagster_obstore/gcs/resource.py
dagster_obstore/s3/__init__.py
dagster_obstore/s3/compute_log_manager.py
dagster_obstore/s3/resource.py
dagster_obstore-0.2.3.dist-info/METADATA
dagster_obstore-0.2.3.dist-info/WHEEL
dagster_obstore-0.2.3.dist-info/RECORD
