Metadata-Version: 2.4
Name: dagster-obstore
Version: 0.2.3
Summary: Dagster integration with `obstore` a python binding to Rust object-store crate. Integration provides computeLogManagers for S3, ADLS & GCS and ObjectStore resourecs
Requires-Python: >=3.9
Requires-Dist: dagster>=1.10.7
Requires-Dist: obstore>=0.6.0
